clebs_puc_csv_converter/__init__.py
clebs_puc_csv_converter/converter.py
clebs_puc_csv_converter-0.1.4.dist-info/entry_points.txt
clebs_puc_csv_converter-0.1.4.dist-info/WHEEL
clebs_puc_csv_converter-0.1.4.dist-info/METADATA
clebs_puc_csv_converter-0.1.4.dist-info/RECORD
