Metadata-Version: 2.1
Name: clebs-puc-csv-converter
Version: 0.1.4
Summary: Convert csv to json. Publishing only for learning purposes at PUC.
Author: Clebson Cardoso
Author-email: clebsondm@gmail.com
Requires-Python: >=3.9,<4.0
Classifier: Programming Language :: Python :: 3
Classifier: Programming Language :: Python :: 3.9
Requires-Dist: click (>=8.0.1,<9.0.0)
Requires-Dist: pandas (>=1.3.3,<2.0.0)
